cpu_modules.v
/******************************* 
    MEMORY 32x8 bidirectional
    - read when rw = 0
    - write when rw = 1
    - sync with clock
*******************************/
module memory32x8_bi
(
    input clk, rw, en,
    input [4:0] addr,
    inout [7:0] data
);
reg [7:0] memory [31:0];
reg [7:0] data_out;

assign data = (en & !rw) ? (data_out) : 8'bz;

always @(posedge clk) begin
    if(en)
        if(!rw)
            data_out <= memory[addr];
        else
            data_out <= 8'bz;
end
always @(negedge clk) begin
    if(en)
        if(rw)
            memory[addr] <= data; 
end
endmodule

/*******************************
    MUTIFLEXER N bits
*******************************/
module muxNbits
#(parameter N=5)(
    input [N-1:0] in_0, in_1,
    input sel,
    output [N-1:0] out
);
assign out = sel ? in_1 : in_0;
endmodule

/*******************************
    REGISTER N bits
    - reset sync with posedge clock
    - work with posedge clock
*******************************/
module registerNbits
#(
    parameter N = 8
)(
    input [N-1:0] in,
    input clk, rst, load,
    output reg [N-1:0] out
);

always @(posedge clk) begin
    if(rst)
        out <= 0;
    else if(load)
        out <= in;
end
endmodule
/*******************************
    COUNTER

    - load async
    - reset async
    - work with posedge clock
*******************************/
module counterNbits
#(parameter N = 5)(
    input clk, rst, load,
    input [N-1:0] preset,
    output reg [N-1:0] out = 0
);
/* reg [N-1:0] count = 0; */
always @(posedge clk) begin
    if(!load && !rst) begin
        out <= out + 1;
    end
end
always @(load, rst) begin
    if(rst)
        out = 0;
    else if(load)
        out = preset;
end

endmodule

/*******************************
    ALU 
*******************************/
/* TODO */
/*******************************
    CONTROL
*******************************/
/* TODO */

memory32x8_bi_tb.v
`timescale 1ns/1ps

module memory32x8_bi_tb();
reg clk, rw, en;
reg [4:0] addr;
reg [7:0] input_data;
wire [7:0] data; /* inout data */

initial begin
clk = 1'b1;
forever #5 clk = ~clk;
end

assign data = rw ? input_data : 8'bz;

initial begin
    $dumpfile("memory32x8_bi_tb.vcd");
    $dumpvars(0, memory32x8_bi_tb);
    {en, rw, addr, input_data} = 15'b1_0_00000_00000000;
    #20 {en, rw, addr, input_data} = 15'b1_1_00001_00000010;
    #6 {en, rw, addr, input_data} = 15'b1_0_00001_00000000;
    #3 {en, rw, addr, input_data} = 15'b1_0_00001_00000000;
    #20 {en, rw, addr, input_data} = 15'b1_0_00010_00000000;
    #20 {en, rw, addr, input_data} = 15'b1_0_00001_00000000;
    
    #10
    $finish;
end
memory32x8_bi mem(.data(data), .clk(clk), .en(en), .rw(rw), .addr(addr));
endmodule

memory32x8_bi_tb.vcd
$date
	Wed Nov  6 17:28:42 2024
$end
$version
	Icarus Verilog
$end
$timescale
	1ps
$end
$scope module memory32x8_bi_tb $end
$var wire 8 ! data [7:0] $end
$var reg 5 " addr [4:0] $end
$var reg 1 # clk $end
$var reg 1 $ en $end
$var reg 8 % input_data [7:0] $end
$var reg 1 & rw $end
$scope module mem $end
$var wire 5 ' addr [4:0] $end
$var wire 1 # clk $end
$var wire 8 ( data [7:0] $end
$var wire 1 $ en $end
$var wire 1 & rw $end
$var reg 8 ) data_out [7:0] $end
$upscope $end
$upscope $end
$enddefinitions $end
#0
$dumpvars
bx )
bx (
b0 '
0&
b0 %
1$
1#
b0 "
bx !
$end
#5000
0#
#10000
1#
#15000
0#
#20000
bz )
b10 !
b10 (
1#
1&
b1 "
b1 '
b10 %
#25000
0#
#26000
bz !
bz (
0&
b0 %
#30000
b10 !
b10 (
b10 )
1#
#35000
0#
#40000
1#
#45000
0#
#49000
b10 "
b10 '
#50000
bx !
bx (
bx )
1#
#55000
0#
#60000
1#
#65000
0#
#69000
b1 "
b1 '
#70000
b10 !
b10 (
b10 )
1#
