Simple-RISC/cpu_modules.v
/******************************* 
    MEMORY 32x8 bidirectional
    - read when rw = 0
    - write when rw = 1
    - sync with clock
*******************************/
module memory32x8_bi
(
    input clk, rw, en,
    input [4:0] addr,
    inout [7:0] data
);
reg [7:0] memory [31:0];
reg [7:0] data_out;

assign data = (en & !rw) ? (data_out) : 8'bz;

always @(posedge clk) begin
    if(en)
        if(!rw)
            data_out <= memory[addr];
        else if(rw)
            memory[addr] <= data; 
end
endmodule

/*******************************
    MUTIFLEXER N bits
*******************************/
module muxNbits
#(parameter N=5)(
    input [N-1:0] in_0, in_1,
    input sel,
    output [N-1:0] out
);
assign out = sel ? in_1 : in_0;
endmodule

/*******************************
    REGISTER N bits
    - reset sync with posedge clock
    - work with posedge clock
*******************************/
module registerNbits
#(
    parameter N = 8
)(
    input [N-1:0] in,
    input clk, rst, load,
    output reg [N-1:0] out
);

always @(posedge clk) begin
    if(rst)
        out <= 0;
    else if(load)
        out <= in;
end
endmodule
/*******************************
    REGISTER N bits
    - reset sync with posedge clock
    - work with negedge clock
*******************************/
module registerNbits_neg
#(
    parameter N = 8
)(
    input [N-1:0] in,
    input clk, rst, load,
    output reg [N-1:0] out
);

always @(negedge clk) begin
    if(rst)
        out <= 0;
    else if(load)
        out <= in;
end
endmodule
/*******************************
    COUNTER

    - load async
    - reset async
    - work with posedge clock
*******************************/
module counterNbits
#(parameter N = 5)(
    input clk, rst, load,
    input [N-1:0] preset,
    output reg [N-1:0] out = 0
);
/* reg [N-1:0] count = 0; */
always @(posedge clk) begin
    if(!load && !rst) begin
        out <= out + 1;
    end
end
always @(load, rst) begin
    if(rst)
        out = 0;
    else if(load)
        out = preset;
end

endmodule

/*******************************
    ALU 
*******************************/
module ALU (
    input [7:0] inA,           // Toán h?ng ??u vào A (8-bit)
    input [7:0] inB,           // Toán h?ng ??u vào B (8-bit)
    input [2:0] opcode,        // Mã l?nh ?i?u khi?n (3-bit)
    output reg [7:0] result,   // K?t qu? ??u ra (8-bit)
    output reg is_zero         // C? ki?m tra n?u k?t qu? b?ng 0
);

// ??nh ngh?a các mã l?nh
localparam HLT = 3'b000;
localparam SKZ = 3'b001;
localparam ADD = 3'b010;
localparam AND_OP = 3'b011;
localparam XOR_OP = 3'b100;
localparam LDA = 3'b101;
localparam STO = 3'b110;
localparam JMP = 3'b111;

always @(*) begin
    case (opcode)
        HLT: begin
            // D?ng ho?t ??ng ch??ng trình
            result = 8'b00000000;
        end
        SKZ: begin
            // B? qua l?nh ti?p theo n?u result b?ng 0
            if (result == 8'b00000000) begin
                is_zero = 1'b1;
            end else begin
                is_zero = 1'b0;
            end
        end
        ADD: begin
            // C?ng inA và inB, l?u k?t qu? vào result
            result = inA + inB;
        end
        AND_OP: begin
            // Th?c hi?n AND gi?a inA và inB
            result = inA & inB;
        end
        XOR_OP: begin
            // Th?c hi?n XOR gi?a inA và inB
            result = inA ^ inB;
        end
        LDA: begin
            // ??c giá tr? t? ??a ch? trong l?nh và ??a vào Accumulator
            result = inB;  // Gi? ??nh inB ch?a d? li?u c?n n?p vào Accumulator
        end
        STO: begin
            // Ghi d? li?u t? Accumulator vào ??a ch? trong l?nh
            result = inA;  // Gi? ??nh inA ch?a d? li?u c?n ghi
        end
        JMP: begin
            // Nh?y ??n ??a ch? ch? ??nh trong câu l?nh
            result = inA;  // Dùng inA làm ??a ch? nh?y
        end
        default: begin
            result = 8'b00000000;  // Giá tr? m?c ??nh cho result
        end
    endcase
    is_zero = (result == 8'b00000000) ? 1'b1 : 1'b0;
end
endmodule

/*******************************
    BUFFER N bits
    - 3 state
*******************************/
module bufferNbits
#(parameter N=8)(
    input [N-1:0] in,
    input en,
    output [N-1:0] out
);
assign out = en ? in : 'bz;
endmodule
/*******************************
    CONTROL
*******************************/
/* TODO */

alu_tb.v
`timescale 1ns / 1ps

module ALU_tb;

    reg [7:0] inA;           // Toán h?ng ??u vào A
    reg [7:0] inB;           // Toán h?ng ??u vào B
    reg [2:0] opcode;        // Mã l?nh ?i?u khi?n
    wire [7:0] result;       // K?t qu? ??u ra
    wire is_zero;            // C? ki?m tra k?t qu? b?ng 0

    // Kh?i t?o mô-?un ALU
    ALU uut (
        .inA(inA),
        .inB(inB),
        .opcode(opcode),
        .result(result),
        .is_zero(is_zero)
    );

    // Kh?i t?o testbench
    initial begin

    $dumpfile("alu_tb.vcd");
    $dumpvars(0, alu_tb);

        // Test 1: L?nh HLT (000) - D?ng ho?t ??ng ch??ng trình
        opcode = 3'b000;
        inA = 8'b00000000;
        inB = 8'b00000000;
        #10;
        $display("Test HLT - Result: %b, is_zero: %b", result, is_zero);

        // Test 2: L?nh SKZ (001) - B? qua n?u k?t qu? b?ng 0
        opcode = 3'b001;
        inA = 8'b00000000;
        inB = 8'b00000000;
        #10;
        $display("Test SKZ (result = 0) - is_zero: %b", is_zero);

        // Test 3: L?nh SKZ (001) - Không b? qua n?u k?t qu? khác 0
        opcode = 3'b001;
        inA = 8'b00000001;
        inB = 8'b00000001;
        #10;
        $display("Test SKZ (result != 0) - is_zero: %b", is_zero);

        // Test 4: L?nh ADD (010) - C?ng 2 s? (5 + 10)
        opcode = 3'b010;
        inA = 8'b00000101;   // 5
        inB = 8'b00001010;   // 10
        #10;
        $display("Test ADD - Result: %d, is_zero: %b", result, is_zero);

        // Test 5: L?nh AND (011) - AND 2 s? (5 AND 3)
        opcode = 3'b011;
        inA = 8'b00000101;   // 5 (00000101)
        inB = 8'b00000011;   // 3 (00000011)
        #10;
        $display("Test AND - Result: %b, is_zero: %b", result, is_zero);

        // Test 6: L?nh XOR (100) - XOR 2 s? (5 XOR 3)
        opcode = 3'b100;
        inA = 8'b00000101;   // 5 (00000101)
        inB = 8'b00000011;   // 3 (00000011)
        #10;
        $display("Test XOR - Result: %b, is_zero: %b", result, is_zero);

        // Test 7: L?nh LDA (101) - N?p d? li?u vào Accumulator (inB = 15)
        opcode = 3'b101;
        inA = 8'b00000000;
        inB = 8'b00001111;   // 15
        #10;
        $display("Test LDA - Result: %d, is_zero: %b", result, is_zero);

        // Test 8: L?nh STO (110) - Ghi d? li?u t? Accumulator (inA = 20)
        opcode = 3'b110;
        inA = 8'b00010100;   // 20
        inB = 8'b00000000;
        #10;
        $display("Test STO - Result: %d, is_zero: %b", result, is_zero);

        // Test 9: L?nh JMP (111) - Nh?y ??n ??a ch? inA (gi? ??nh inA = 25)
        opcode = 3'b111;
        inA = 8'b00011001;   // 25
        inB = 8'b00000000;
        #10;
        $display("Test JMP - Result: %d, is_zero: %b", result, is_zero);

        // Test 10: L?nh ADD (010) - Ki?m tra is_zero khi k?t qu? là 0
        opcode = 3'b010;
        inA = 8'b00000001;   // 1
        inB = 8'b11111111;   // -1 (d?ng bù 2)
        #10;
        $display("Test ADD (result = 0) - Result: %d, is_zero: %b", result, is_zero);

        $stop;
    end
endmodule

Simple-RISC/ALU_tb.vcd
$date
	Thu Nov 28 15:38:12 2024
$end
$version
	Icarus Verilog
$end
$timescale
	1ps
$end
$scope module ALU_tb $end
$var wire 8 ! result [7:0] $end
$var wire 1 " is_zero $end
$var reg 8 # inA [7:0] $end
$var reg 8 $ inB [7:0] $end
$var reg 3 % opcode [2:0] $end
$scope module uut $end
$var wire 8 & inA [7:0] $end
$var wire 8 ' inB [7:0] $end
$var wire 3 ( opcode [2:0] $end
$var reg 1 " is_zero $end
$var reg 8 ) result [7:0] $end
$upscope $end
$upscope $end
$enddefinitions $end
#0
$dumpvars
b0 )
b0 (
b0 '
b0 &
b0 %
b0 $
b0 #
1"
b0 !
$end
#10000
b1 %
b1 (
#20000
b1 $
b1 '
b1 #
b1 &
#30000
0"
b1111 !
b1111 )
b1010 $
b1010 '
b101 #
b101 &
b10 %
b10 (
#40000
b1 !
b1 )
b11 $
b11 '
b11 %
b11 (
#45000
1"
b0 !
b0 )
b100 #
b100 &
#50000
0"
b110 !
b110 )
b101 #
b101 &
b100 %
b100 (
#60000
b1111 !
b1111 )
b1111 $
b1111 '
b0 #
b0 &
b101 %
b101 (
#70000
b10100 !
b10100 )
b0 $
b0 '
b10100 #
b10100 &
b110 %
b110 (
#80000
b11001 !
b11001 )
b11001 #
b11001 &
b111 %
b111 (
#90000
1"
b0 !
b0 )
b11111111 $
b11111111 '
b1 #
b1 &
b10 %
b10 (
