Simple-RISC/memory32x8_bi.v
module memory32x8_bi
(
    input clk, rw, en,
    input [4:0] addr,
    inout [7:0] data
);
reg [7:0] memory [31:0];
reg [7:0] data_out;

assign data = (en & !rw) ? (data_out) : 8'bz;

always @(posedge clk) begin
    if(en)
        if(!rw)
            data_out <= memory[addr];
        else if(rw)
            memory[addr] <= data; 
end
endmodule

memory32x8_bi_tb.v
`timescale 1ns/1ps

module memory32x8_bi_tb();
reg clk, rw, en;
reg [4:0] addr;
reg [7:0] input_data; // driven value
wire [7:0] data; /* inout data */
wire [7:0] vision;
initial begin
clk = 1'b1;
forever #5 clk = ~clk;
end

assign data = rw ? input_data : 8'bz;

/* assign data = input_data; */
/* assign vision = data; */

initial begin
    $dumpfile("memory32x8_bi_tb.vcd");
    $dumpvars(0, memory32x8_bi_tb);
    {en, rw, addr, input_data} = 15'b1_0_00000_00000000;
    #18 {en, rw, addr, input_data} = 15'b1_1_00001_00000010;
    #6 {en, rw, addr, input_data} = 15'b1_0_00001_00000000;
    #3 {en, rw, addr, input_data} = 15'b1_0_00001_00000000;
    #20 {en, rw, addr, input_data} = 15'b1_0_00010_00000000;
    #20 {en, rw, addr, input_data} = 15'b1_0_00001_00000000;
    
    #10
    $finish;
end
memory32x8_bi mem(.data(data), .clk(clk), .en(en), .rw(rw), .addr(addr));
endmodule

Simple-RISC/memory32x8_bi_tb.vcd
$date
	Fri Nov 29 21:17:24 2024
$end
$version
	Icarus Verilog
$end
$timescale
	1ps
$end
$scope module memory32x8_bi_tb $end
$var wire 8 ! data [7:0] $end
$var reg 5 " addr [4:0] $end
$var reg 1 # clk $end
$var reg 1 $ en $end
$var reg 8 % input_data [7:0] $end
$var reg 1 & rw $end
$scope module mem $end
$var wire 5 ' addr [4:0] $end
$var wire 1 # clk $end
$var wire 8 ( data [7:0] $end
$var wire 1 $ en $end
$var wire 1 & rw $end
$var reg 8 ) data_out [7:0] $end
$upscope $end
$upscope $end
$enddefinitions $end
#0
$dumpvars
bx )
bx (
b0 '
0&
b0 %
1$
1#
b0 "
bx !
$end
#5000
0#
#10000
1#
#15000
0#
#18000
b10 !
b10 (
1&
b1 "
b1 '
b10 %
#20000
1#
#24000
bx !
bx (
0&
b0 %
#25000
0#
#30000
b10 !
b10 (
b10 )
1#
#35000
0#
#40000
1#
#45000
0#
#47000
b10 "
b10 '
#50000
bx !
bx (
bx )
1#
#55000
0#
#60000
1#
#65000
0#
#67000
b1 "
b1 '
#70000
b10 !
b10 (
b10 )
1#
